langchain_hana_prototype/__init__.py
langchain_hana_prototype/embeddings.py
langchain_hana_prototype/py.typed
langchain_hana_prototype/query_constructors.py
langchain_hana_prototype/utils.py
langchain_hana_prototype/vectorstores.py
langchain_hana_prototype-1.1.0.dist-info/LICENSE
langchain_hana_prototype-1.1.0.dist-info/LICENSES/Apache-2.0.txt
langchain_hana_prototype-1.1.0.dist-info/METADATA
langchain_hana_prototype-1.1.0.dist-info/WHEEL
langchain_hana_prototype-1.1.0.dist-info/RECORD
