Metadata-Version: 2.1
Name: langchain-hana-prototype
Version: 1.1.0
Summary: An integration package connecting SAP Hana Cloud and LangChain
License: MIT
Requires-Python: >=3.9,<4.0
Classifier: License :: OSI Approved :: MIT License
Classifier: Programming Language :: Python :: 3
Classifier: Programming Language :: Python :: 3.9
Classifier: Programming Language :: Python :: 3.10
Classifier: Programming Language :: Python :: 3.11
Classifier: Programming Language :: Python :: 3.12
Classifier: Programming Language :: Python :: 3.13
Requires-Dist: hdbcli (>=2.23.24,<3.0.0)
Requires-Dist: langchain-core (>=0.3.15,<0.4.0)
Requires-Dist: numpy (>=1.24.0,<2.0.0) ; python_version < "3.12"
Requires-Dist: numpy (>=1.26.0,<3) ; python_version >= "3.12"
